stepwise_plugin/__init__.py
stepwise_plugin/admin.py
stepwise_plugin/apps.py
stepwise_plugin/decorators.py
stepwise_plugin/models.py
stepwise_plugin/stepwise_oauth.py
stepwise_plugin/urls.py
stepwise_plugin/utils.py
stepwise_plugin/api/__init__.py
stepwise_plugin/api/serializers.py
stepwise_plugin/api/urls.py
stepwise_plugin/api/views.py
stepwise_plugin/config/__init__.py
stepwise_plugin/config/api_router.py
stepwise_plugin/config/wsgi.py
stepwise_plugin/dashboard/__init__.py
stepwise_plugin/dashboard/utils.py
stepwise_plugin/dashboard/views.py
stepwise_plugin/locale/__init__.py
stepwise_plugin/locale/utils.py
stepwise_plugin/locale/views.py
stepwise_plugin/management/__init__.py
stepwise_plugin/management/commands/__init__.py
stepwise_plugin/management/commands/configure_stepwise_api.py
stepwise_plugin/management/commands/configure_stepwise_locale.py
stepwise_plugin/management/commands/configure_stepwise_marketing_site.py
stepwise_plugin/migrations/0001_initial.py
stepwise_plugin/migrations/0002_ecommerce.py
stepwise_plugin/migrations/0003_alter_ecommerceconfiguration_course_id.py
stepwise_plugin/migrations/0004_auto_20221020_2211.py
stepwise_plugin/migrations/__init__.py
stepwise_plugin/settings/__init__.py
stepwise_plugin/settings/common.py
stepwise_plugin/settings/local.py
stepwise_plugin/settings/production.py
stepwise_plugin/student/__init__.py
stepwise_plugin/student/registration.py
stepwise_plugin/student/session.py
tests/__init__.py
tests/test_locale.py
stepwise_edx_plugin-14.0.17.dist-info/LICENSE.txt
stepwise_edx_plugin-14.0.17.dist-info/METADATA
stepwise_edx_plugin-14.0.17.dist-info/WHEEL
stepwise_edx_plugin-14.0.17.dist-info/entry_points.txt
stepwise_edx_plugin-14.0.17.dist-info/top_level.txt
stepwise_edx_plugin-14.0.17.dist-info/RECORD
