Metadata-Version: 2.1
Name: stepwise-edx-plugin
Version: 14.0.17
Summary: A Django plugin to add Stepwise Math custom features to Open edX installations.
Home-page: https://github.com/StepwiseMath/stepwise-edx-plugin
Author: Lawrence McDaniel
Author-email: Lawrence McDaniel <lpm0073@gmail.com>, Kent Fuka <kent@querium.com>
Project-URL: Homepage, https://github.com/StepwiseMath/stepwise-edx-plugin
Project-URL: Bug Tracker, https://github.com/StepwiseMath/stepwise-edx-plugin/issues
Project-URL: Repository, https://github.com/StepwiseMath/stepwise-edx-plugin
Keywords: Open edX,api,Stepwise,QueriumCorp
Classifier: Programming Language :: Python :: 3
Classifier: License :: OSI Approved :: MIT License
Classifier: Operating System :: OS Independent
Requires-Python: >=3.8
License-File: LICENSE.txt
Requires-Dist: social-auth-core (==4.2.0)
Requires-Dist: social-auth-app-django (==5.0.0)
Requires-Dist: Django (>=3.2)
Provides-Extra: common
Requires-Dist: Django (>=3.2) ; extra == 'common'
Provides-Extra: local
Requires-Dist: pre-commit ; extra == 'local'
Requires-Dist: black ; extra == 'local'
Requires-Dist: flake8 ; extra == 'local'
Requires-Dist: ipython ; extra == 'local'
